libcoffee/__init__.py
libcoffee/common/__init__.py
libcoffee/common/executablebase.py
libcoffee/common/path.py
libcoffee/common/sdffile.py
libcoffee/core/__init__.py
libcoffee/core/molbase.py
libcoffee/docking/__init__.py
libcoffee/docking/docking_region.py
libcoffee/docking/conformer_generator/__init__.py
libcoffee/docking/conformer_generator/conformergeneratorbase.py
libcoffee/docking/conformer_generator/omega.py
libcoffee/docking/docking/__init__.py
libcoffee/docking/docking/dockingtoolbase.py
libcoffee/docking/docking/advina/__init__.py
libcoffee/docking/docking/advina/autodockvina.py
libcoffee/docking/docking/restretto/__init__.py
libcoffee/docking/docking/restretto/atomgrid-gen
libcoffee/docking/docking/restretto/config.py
libcoffee/docking/docking/restretto/conformer-docking
libcoffee/docking/docking/restretto/executable.py
libcoffee/docking/state_generator/__init__.py
libcoffee/docking/state_generator/ligprep.py
libcoffee/docking/state_generator/stategeneratorbase.py
libcoffee/fragment/__init__.py
libcoffee/fragment/decompose/__init__.py
libcoffee/fragment/decompose/decompose
libcoffee/fragment/decompose/decompose.py
libcoffee/fragment/fbdb/__init__.py
libcoffee/fragment/fbdb/executable.py
libcoffee/metrics/__init__.py
libcoffee/metrics/enrichment_factor.py
libcoffee/openbabeltools/__init__.py
libcoffee/openbabeltools/_util.py
libcoffee/openbabeltools/mol.py
libcoffee/openbabeltools/test_openbabel_mol.py
libcoffee/rdkittools/__init__.py
libcoffee/rdkittools/mol.py
libcoffee/rdkittools/test_rdkit_mol.py
libcoffee/rdkittools/util.py
libcoffee-0.4.3.dist-info/LICENSE
libcoffee-0.4.3.dist-info/METADATA
libcoffee-0.4.3.dist-info/WHEEL
libcoffee-0.4.3.dist-info/top_level.txt
libcoffee-0.4.3.dist-info/RECORD
